utility.py
ai_dq_module-1.1.0.dist-info/METADATA
ai_dq_module-1.1.0.dist-info/WHEEL
ai_dq_module-1.1.0.dist-info/top_level.txt
ai_dq_module-1.1.0.dist-info/RECORD
