Metadata-Version: 2.1
Name: ai-dq-module
Version: 1.1.0
Summary: data quality rules check
Author: Himanshu
Author-email: himanshu.tomar@decisionpoint.in
Classifier: Programming Language :: Python :: 3
Classifier: License :: OSI Approved :: MIT License
Classifier: Operating System :: OS Independent
Requires-Python: >=3.8
Requires-Dist: openai
